guapy/__init__.py
guapy/cli.py
guapy/client_connection.py
guapy/config.py
guapy/crypto.py
guapy/exceptions.py
guapy/filter.py
guapy/guacd_client.py
guapy/models.py
guapy/py.typed
guapy/server.py
guapy-1.0.0.dist-info/METADATA
guapy-1.0.0.dist-info/WHEEL
guapy-1.0.0.dist-info/entry_points.txt
guapy-1.0.0.dist-info/licenses/LICENSE
guapy-1.0.0.dist-info/RECORD
