Metadata-Version: 2.4
Name: guapy
Version: 1.0.0
Summary: Python implementation of Guacamole WebSocket proxy server
Project-URL: Homepage, https://github.com/Adithya1331/guapy
Project-URL: Documentation, https://guapy.readthedocs.io
Project-URL: Repository, https://github.com/Adithya1331/guapy.git
Project-URL: Issues, https://github.com/Adithya1331/guapy/issues
Project-URL: Changelog, https://github.com/Adithya1331/guapy/blob/main/CHANGELOG.md
Author-email: Adithya <adithyakokkirala@gmail.com>
Maintainer-email: Adithya <adithyakokkirala@gmail.com>
License-Expression: MIT
License-File: LICENSE
Keywords: guacamole,proxy,rdp,remote-desktop,ssh,vnc,websocket
Classifier: Development Status :: 4 - Beta
Classifier: Framework :: AsyncIO
Classifier: Framework :: FastAPI
Classifier: Intended Audience :: Developers
Classifier: Intended Audience :: System Administrators
Classifier: License :: OSI Approved :: MIT License
Classifier: Operating System :: OS Independent
Classifier: Programming Language :: Python :: 3
Classifier: Programming Language :: Python :: 3.9
Classifier: Programming Language :: Python :: 3.10
Classifier: Programming Language :: Python :: 3.11
Classifier: Programming Language :: Python :: 3.12
Classifier: Programming Language :: Python :: 3.13
Classifier: Topic :: Communications
Classifier: Topic :: Internet :: WWW/HTTP :: HTTP Servers
Classifier: Topic :: System :: Networking
Requires-Python: >=3.9
Requires-Dist: cryptography>=41.0.0
Requires-Dist: fastapi>=0.104.0
Requires-Dist: httpx>=0.28.1
Requires-Dist: pydantic>=2.5.0
Requires-Dist: python-dotenv>=1.0.0
Requires-Dist: starlette>=0.47.2
Requires-Dist: typer>=0.16.0
Requires-Dist: uvicorn[standard]>=0.24.0
Requires-Dist: websockets>=12.0
